{"story":{"group_1":[{"item":[{"path":"resource/scenario/img/51023_singleraid_suzune/51023_title13.jpg","posX":0,"posY":0,"visible":"appear"}],"turnChangeIn":"fadeIn","turnChangeOut":"fadeOut"},{"autoTurnLast":0.5,"item":[{"path":"resource/scenario/img/51023_singleraid_suzune/51023_title13.jpg","visible":"hide"}],"turnChangeIn":"fadeIn"},{"bgm":"bgm03_story02","nameNarration":"詩音 千里","narration":"夏目書房に着いて@いよいよ本格的に@絵本の捜索が始まった…","narrationBg":"bg_adv_narration.jpg","narrationEffect":"in","turnChangeOut":"fadeOut"},{"chara":[{"cheek":0,"face":"mtn_ex_050.exp.json","id":403301,"motion":0,"pos":1}],"narration":"…はずなのだが…"},{"bg":"bg_adv_13091.jpg","chara":[{"id":403301}],"nameCenter":"成見 亜里紗","narrationEffect":"out","textCenter":"…これ…"},{"autoTurnLast":0.01,"chara":[{"id":403301,"pos":0}],"textClear":1},{"chara":[{"cheek":0,"face":"mtn_ex_050.exp.json","id":403401,"motion":400,"pos":2}],"nameRight":"詩音 千里","textRight":"[chara:403401:effect_emotion_surprise_0][se:7226_shock]…何!?@見つけたの!?"},{"chara":[{"cheek":0,"face":"mtn_ex_010.exp.json","id":403301,"motion":1}],"nameLeft":"成見 亜里紗","textLeft":"…チサト、ほら…"},{"chara":[{"id":403301}],"textLeft":"この本…知ってる？"},{"chara":[{"id":403401}],"textRight":"え…？"},{"chara":[{"cheek":0,"face":"mtn_ex_030.exp.json","id":403401,"motion":200}],"textRight":"…なんだ…"},{"chara":[{"id":403401}],"textRight":"「おだんごくんのぼうけん」じゃ@ないじゃない…"},{"chara":[{"cheek":0,"face":"mtn_ex_030.exp.json","id":403301,"motion":0}],"textLeft":"…ごめんごめん"},{"chara":[{"id":403401,"motion":1}],"textRight":"ここでも寄り道～？"},{"chara":[{"cheek":0,"face":"mtn_ex_010.exp.json","id":403301}],"textLeft":"でもさ、ほら…"},{"chara":[{"id":403401}],"textRight":"え～？"},{"chara":[{"id":403301,"motion":100}],"textLeft":"ちょっと読んでみてよ！"},{"chara":[{"id":403401,"motion":300}],"textRight":"…も～…"},{"chara":[{"id":403401}],"textRight":"…えっと…"},{"nameNarration":"詩音 千里","narration":"昔々あるところに@小さな村がありました","narrationBg":"bg_adv_narration.jpg","narrationEffect":"in"},{"narration":"ある時、村に@人に化けた狼がやってきました"},{"narration":"狼は夜になると@毎日のように村の人達を@襲っていました"},{"narration":"森に住む心優しい魔女は@村人達をかわいそうに思い@魔法で狼をやっつけてあげました"},{"chara":[{"id":403401,"motion":0},{"cheek":0,"face":"mtn_ex_030.exp.json","id":403301,"motion":1}],"narration":"村は平和になりましたが@自分が疑われるのを恐れた村人達は@今までのことを魔女のしわざにして@村から追い出してしまいました"},{"chara":[{"id":403401,"lipSynch":0}],"narrationEffect":"out","textRight":"…………"},{"chara":[{"id":403301,"lipSynch":0}],"textLeft":"…………"},{"chara":[{"id":403401,"lipSynch":1}],"textRight":"…悲しい話だね"},{"chara":[{"id":403301,"lipSynch":1}],"textLeft":"…そうなんだよね"},{"chara":[{"id":403401}],"textRight":"でも…"},{"chara":[{"cheek":0,"face":"mtn_ex_020.exp.json","id":403401,"motion":1}],"textRight":"「魔女」っていうのは@引っかかるかな"},{"chara":[{"id":403401}],"surround":"7202_telepathy","textRight":"魔法少女としてはさ","turnEffect":"ef_adv_02"},{"chara":[{"cheek":0,"face":"mtn_ex_050.exp.json","id":403301}],"textLeft":"…ま、それはあるけど…"},{"chara":[{"cheek":0,"face":"mtn_ex_030.exp.json","id":403301,"motion":0}],"surround":"stop","textLeft":"ひとりぼっちになるのが…ね","turnEffect":"stop"},{"chara":[{"cheek":0,"face":"mtn_ex_030.exp.json","id":403401}],"textRight":"…アリサ…"},{"chara":[{"id":403401,"lipSynch":0,"motion":300}],"textRight":"（昔の自分と重ねてるのかな…）","turnEffect":"thinking"},{"chara":[{"cheek":0,"face":"mtn_ex_010.exp.json","id":403301}],"textLeft":"…この本、まだ続きがある@みたいだけど…","turnEffect":"stop"},{"chara":[{"cheek":0,"face":"mtn_ex_050.exp.json","id":403401,"lipSynch":1,"motion":400}],"textRight":"…ほ、ほらほら！@それはまた今度！"},{"chara":[{"cheek":0,"face":"mtn_ex_010.exp.json","id":403401,"motion":1}],"textRight":"一緒に探してくれるんじゃ@なかったの～？"},{"chara":[{"cheek":0,"face":"mtn_ex_050.exp.json","id":403301,"lipSynch":0}],"textLeft":"…………"},{"chara":[{"cheek":0,"face":"mtn_ex_011.exp.json","id":403301,"lipSynch":1,"motion":100}],"textLeft":"…そうだった！@あはは…ついついね"},{"chara":[{"cheek":0,"face":"mtn_ex_010.exp.json","id":403301,"motion":200}],"textLeft":"さーて、本気出しちゃうよ～！"},{"chara":[{"cheek":0,"face":"mtn_ex_030.exp.json","id":403401,"motion":200}],"textRight":"最初からでお願い@したいんだけど…！"},{"chara":[{"cheek":0,"face":"mtn_ex_030.exp.json","id":403301,"motion":1,"pos":0},{"cheek":0,"face":"mtn_ex_030.exp.json","id":403401,"motion":0,"pos":2}],"nameNarration":"詩音 千里","narration":"それからも私たちは@夏目書房の本棚を隈なく探したが…","narrationBg":"bg_adv_narration.jpg","narrationEffect":"in","turnChangeIn":"fadeIn","turnChangeOut":"fadeOut"},{"chara":[{"id":403301}],"narrationEffect":"out","textLeft":"ダメだ…"},{"chara":[{"id":403401,"motion":300}],"textRight":"見つからないね…"},{"chara":[{"cheek":0,"face":"mtn_ex_011.exp.json","id":301101,"motion":1,"pos":0}],"nameLeft":"夏目 かこ","textLeft":"あの～…"},{"chara":[{"cheek":0,"face":"mtn_ex_010.exp.json","id":403401,"motion":400}],"textRight":"あ、どうでしたか!?"},{"chara":[{"id":301101}],"textLeft":"それが…"},{"autoTurnLast":2.0,"turnChangeIn":"fadeIn"}]},"version":3}