{"story":{"group_1":[{"bg":"bg_adv_12021.jpg","bgm":"bgm03_story08","chara":[{"cheek":0,"face":"mtn_ex_020.exp.json","id":303201,"lipSynch":0,"motion":0,"pos":1}],"nameCenter":"梢 麻友","textCenter":"…………","turnChangeIn":"fadeIn","turnChangeOut":"fadeOut"},{"chara":[{"cheek":0,"face":"mtn_ex_030.exp.json","id":303201,"lipSynch":0}],"textCenter":"（勝てたけど…@使い魔だけ…？）","turnEffect":"thinking"},{"chara":[{"id":303201,"lipSynch":0}],"textCenter":"（倒した魔女の使い魔だけが@行動するなんてことあるのかな）"},{"chara":[{"id":303201,"lipSynch":0,"motion":300}],"textCenter":"（しかも、明らかに私を狙って@現れたような…）"},{"chara":[{"cheek":0,"face":"mtn_ex_050.exp.json","id":303201,"lipSynch":0}],"textCenter":"（昨日、魔女を倒したから…？）"},{"autoTurnLast":0.01,"chara":[{"cheek":0,"face":"mtn_ex_030.exp.json","id":101301,"motion":0,"pos":1}],"turnChangeIn":"fadeIn","turnEffect":"stop"},{"bg":"bg_adv_19041.jpg","chara":[{"id":101301}],"textCenter":"麻友先輩、お怪我は？@執拗に狙われていたようですが…","turnChangeOut":"fadeOut","turnEffect":"blackFrame"},{"autoTurnLast":0.01,"chara":[{"cheek":0,"face":"mtn_ex_030.exp.json","id":303201,"motion":1,"pos":1}],"turnChangeIn":"fadeIn","turnEffect":"stop"},{"bg":"bg_adv_12021.jpg","chara":[{"id":303201,"lipSynch":0}],"nameCenter":"梢 麻友","textCenter":"（そういえば、昨日も@何故か私ばかり狙われて…）","turnChangeOut":"fadeOut","turnEffect":"thinking"},{"chara":[{"id":303201,"motion":100}],"textCenter":"どうして…？","turnEffect":"stop"},{"chara":[{"id":303201,"lipSynch":0}],"textCenter":"…………"},{"bgm":"stop","chara":[{"cheek":0,"face":"mtn_ex_050.exp.json","id":303201,"lipSynch":0,"motion":0}],"textCenter":"[chara:303201:effect_ef_adv_01][se:7201_detect_magic]――っ!?"},{"bgm":"bgm03_story10","chara":[{"cheek":0,"face":"mtn_ex_030.exp.json","id":303201}],"textCenter":"また、魔力反応…？"},{"chara":[{"cheek":0,"face":"mtn_ex_050.exp.json","id":303201,"lipSynch":0,"motion":400}],"textCenter":"[chara:303201:effect_ef_adv_01][se:7201_detect_magic]――っ!?@それも、ひとつじゃない？"},{"chara":[{"id":303201,"lipSynch":0}],"textCenter":"（街中のいたるところから@たくさんの反応がある！）","turnEffect":"thinking"},{"chara":[{"cheek":0,"face":"mtn_ex_020.exp.json","id":303201,"motion":200}],"textCenter":"大変…！少しでも@多く倒して街を守らなきゃ！","turnEffect":"stop"},{"chara":[{"eyeClose":1,"id":303201}],"textCenter":"一番近い敵は…"},{"chara":[{"id":303201,"lipSynch":0}],"flashEffect":"flashWhiteSlow2","se":"7211_souljem_02","textCenter":"…………"},{"chara":[{"cheek":0,"eyeClose":0,"face":"mtn_ex_030.exp.json","id":303201,"motion":0}],"textCenter":"美術館…？"},{"chara":[{"id":303201,"lipSynch":0}],"textCenter":"（もしかしたら、また美術品を@盗むつもりかも…）","turnEffect":"thinking"},{"chara":[{"cheek":0,"face":"mtn_ex_020.exp.json","id":303201,"lipSynch":0}],"textCenter":"（行ってみよう）"},{"chara":[{"cheek":0,"face":"mtn_ex_050.exp.json","id":303201,"lipSynch":0,"motion":400}],"textCenter":"[chara:303201:effect_ef_adv_01][se:7201_detect_magic]――っ!?","turnEffect":"stop"},{"chara":[{"cheek":0,"face":"mtn_ex_020.exp.json","id":303201}],"textCenter":"違う…！@ここ!?"},{"autoTurnLast":0.5,"bg":"bg_adv_47001.jpg","bgChangeEffect":"enterWitchSpace","chara":[{"id":303201,"pos":2}],"se":"7208_wander_into","textClear":1},{"chara":[{"id":7001,"name":"sprite_0","pos":0}],"textBg":"shout","textLeft":"シャラー！＋＃￥・＄＠!!"},{"chara":[{"cheek":0,"face":"mtn_ex_030.exp.json","id":303201,"motion":0}],"textRight":"こんなに、続けて@使い魔が襲ってくるなんて…！"},{"chara":[{"cheek":0,"effect":"ef_adv_05","face":"mtn_ex_020.exp.json","id":303200,"motion":100,"pos":2}],"se":"7205_magic_girl","textRight":"…と、とにかく@倒したらすぐに美術館へ！"},{"autoTurnLast":2.0,"turnChangeIn":"fadeIn"}]},"version":3}