{"story":{"group_1":[{"bg":"bg_adv_narration.jpg","bgm":"bgm03_story07","chara":[{"cheek":0,"face":"mtn_ex_030.exp.json","id":304900,"motion":0,"pos":1,"voiceFull":"fullvoice/section_101603/vo_full_101603-2-1"}],"nameCenter":"？？？","textCenter":"やちよ…","turnChangeIn":"fadeIn","turnChangeOut":"fadeOut","turnEffect":"blackFrame"},{"chara":[{"face":"mtn_ex_030.exp.json","id":303700,"motion":0,"pos":1,"tear":0,"voiceFull":"fullvoice/section_101603/vo_full_101603-2-2","voiceFullStop":"fullvoice/section_101603/vo_full_101603-2-1"}],"textCenter":"七海先輩…"},{"autoTurnLast":0.01,"turnChangeIn":"fadeIn","voiceFullStop":"fullvoice/section_101603/vo_full_101603-2-2"},{"autoTurnLast":0.01,"bg":"bg_adv_21201.jpg","narrationBg":"narration","narrationEffect":"in","turnChangeOut":"fadeOut","turnEffect":"stop"},{"nameNarration":"やちよ","narration":"彼女たちは仲間だった…","voiceFull":"fullvoice/section_101603/vo_full_101603-2-3"},{"chara":[{"cheek":0,"face":"mtn_ex_011.exp.json","id":100401,"motion":100,"pos":0},{"cheek":0,"face":"mtn_ex_011.exp.json","id":100501,"motion":100,"pos":2}],"narration":"けど、あの子たちは違う…@あの子たちは協力関係…","voiceFull":"fullvoice/section_101603/vo_full_101603-2-4","voiceFullStop":"fullvoice/section_101603/vo_full_101603-2-3"},{"chara":[{"cheek":0,"face":"mtn_ex_011.exp.json","id":100101,"motion":100,"pos":0},{"cheek":0,"face":"mtn_ex_011.exp.json","id":100301,"motion":101,"pos":2}],"narration":"ただの助手…ただの弟子…","voiceFull":"fullvoice/section_101603/vo_full_101603-2-5","voiceFullStop":"fullvoice/section_101603/vo_full_101603-2-4"},{"autoTurnLast":0.01,"narrationEffect":"out","turnChangeIn":"fadeIn","voiceFullStop":"fullvoice/section_101603/vo_full_101603-2-5"},{"autoTurnLast":0.01,"narrationBg":"bg_adv_narration.jpg","narrationEffect":"in","turnChangeOut":"fadeOut"},{"narration":"あのまま放っておいてもいいの？","voiceFull":"fullvoice/section_101603/vo_full_101603-2-6"},{"narration":"あの子たちは知ることになるわよ？","voiceFull":"fullvoice/section_101603/vo_full_101603-2-7","voiceFullStop":"fullvoice/section_101603/vo_full_101603-2-6"},{"autoTurnLast":0.01,"chara":[{"cheek":-1,"face":"mtn_ex_030.exp.json","id":100201,"motion":0,"pos":1}],"narrationEffect":"out","turnChangeIn":"fadeIn","turnEffect":"thinking","voiceFullStop":"fullvoice/section_101603/vo_full_101603-2-7"},{"chara":[{"cheek":-1,"face":"mtn_ex_030.exp.json","id":100201,"lipSynch":0,"voiceFull":"fullvoice/section_101603/vo_full_101603-2-8"}],"nameCenter":"やちよ","textCenter":"（一応、調べておこう…@[textRed:記憶ミュージアム]について…）","turnChangeOut":"fadeOut"},{"autoTurnLast":2.0,"turnChangeIn":"fadeIn","turnEffect":"stop","voiceFullStop":"fullvoice/section_101603/vo_full_101603-2-8"}]},"version":3}