{"story":{"group_1":[{"autoTurnLast":0.4,"chara":[{"cheek":0,"face":"mtn_ex_010.exp.json","id":200301,"motion":400,"pos":0},{"cheek":0,"face":"mtn_ex_040.exp.json","id":200401,"motion":0,"pos":2}],"turnChangeIn":"fadeIn"},{"bg":"bg_adv_21111.jpg","bgm":"bgm03_story06","chara":[{"cheek":0,"face":"mtn_ex_030.exp.json","id":200401,"motion":300}],"nameRight":"さやか","textRight":"…まどか…ほむら…@…あたしは…","turnChangeOut":"fadeOut"},{"chara":[{"id":200401}],"textRight":"…あたしは、まだ魔法少女に@なって日が浅いから…"},{"chara":[{"cheek":0,"face":"mtn_ex_040.exp.json","id":200401,"motion":100}],"textRight":"そんな危なそうな街に行っても@なかなか…ね？"},{"chara":[{"cheek":0,"face":"mtn_ex_051.exp.json","id":200101,"motion":201,"pos":0}],"nameLeft":"まどか","textLeft":"さやかちゃん、そんな…！"},{"chara":[{"id":200401,"motion":1}],"textRight":"まだ戦いも魔法も@おぼつかないもんね…"},{"chara":[{"id":200401}],"textRight":"だから、ひとりでは@行動しないよ"},{"chara":[{"cheek":0,"face":"mtn_ex_030.exp.json","id":200301,"motion":100,"pos":0}],"nameLeft":"ほむら","textLeft":"美樹さん…！"},{"chara":[{"id":200401,"motion":0}],"textRight":"…ただ、逆にあたしからも@ふたりにお願いがあるんだ…"},{"chara":[{"cheek":0,"face":"mtn_ex_040.exp.json","id":200101,"motion":1,"pos":0}],"nameLeft":"まどか","textLeft":"さやかちゃんから…？"},{"chara":[{"id":200401}],"textRight":"…あのさ…"},{"chara":[{"cheek":0,"face":"mtn_ex_020.exp.json","id":200401,"motion":200}],"textRight":"あたしを神浜に@連れて行ってほしいんだ…！"},{"chara":[{"cheek":0,"face":"mtn_ex_050.exp.json","id":200301,"motion":400,"mouthOpen":1,"pos":0}],"nameLeft":"ほむら","textLeft":"えぇ…!?"},{"chara":[{"cheek":0,"face":"mtn_ex_051.exp.json","id":200101,"motion":400,"pos":0}],"nameLeft":"まどか","textLeft":"さやかちゃん@それって…どうして…!?"},{"chara":[{"id":200401,"motion":300}],"textRight":"分かってはいるんだよ！"},{"chara":[{"id":200401}],"textRight":"いろはって子から情報が入って@それから動いた方がいいのは…"},{"chara":[{"cheek":0,"face":"mtn_ex_030.exp.json","id":200401}],"textRight":"でも…でもさ…"},{"chara":[{"cheek":0,"face":"mtn_ex_020.exp.json","id":200401,"motion":200}],"textRight":"居ても立ってもいられないんだ！"},{"chara":[{"cheek":0,"face":"mtn_ex_020.exp.json","id":200301,"motion":400,"pos":0}],"nameLeft":"ほむら","textLeft":"でも、美樹さん！@本当に神浜は今、とても…！"},{"chara":[{"cheek":0,"face":"mtn_ex_030.exp.json","id":200401,"motion":0}],"textRight":"さっきの話で@十分伝わっているよ"},{"chara":[{"id":200401}],"textRight":"使い魔とか魔女とか@驚くことばかりだったのに…"},{"chara":[{"id":200401,"motion":300}],"textRight":"その上ドッペルとか@ウワサとか…"},{"chara":[{"id":200401}],"textRight":"その上、魔法少女同士で@対立するだなんて…"},{"chara":[{"id":200401,"motion":100}],"textRight":"頭の中、こんがらがってるよ@正直…"},{"chara":[{"cheek":0,"face":"mtn_ex_040.exp.json","id":200101,"lipSynch":0,"motion":0,"pos":0}],"nameLeft":"まどか","textLeft":"…………"},{"chara":[{"cheek":0,"face":"mtn_ex_030.exp.json","id":200101,"motion":300}],"textLeft":"…わたしもだよ…"},{"chara":[{"cheek":0,"face":"mtn_ex_030.exp.json","id":200301,"motion":300,"pos":0}],"nameLeft":"ほむら","textLeft":"整理がまだ…@つかないよね…"},{"chara":[{"cheek":0,"face":"mtn_ex_020.exp.json","id":200401,"motion":0}],"textRight":"…でも、だからといって@ただ待っているのもできないんだ"},{"chara":[{"cheek":0,"face":"mtn_ex_040.exp.json","id":200101,"motion":100,"pos":0}],"nameLeft":"まどか","textLeft":"さやかちゃん…@どうして…？"},{"chara":[{"cheek":0,"face":"mtn_ex_040.exp.json","id":200401}],"textRight":"それは…"},{"chara":[{"cheek":0,"face":"mtn_ex_020.exp.json","id":200401,"motion":1}],"textRight":"あたしの願いが@あるからなんだ…！"},{"autoTurnLast":2.0,"turnChangeIn":"fadeIn"}]},"version":3}