{"story":{"group_1":[{"bg":"bg_adv_21041.jpg","bgm":"bgm01_anime03","chara":[{"cheek":0,"face":"mtn_ex_011.exp.json","id":300601,"motion":0,"pos":0},{"cheek":0,"face":"mtn_ex_030.exp.json","id":200401,"motion":0,"pos":2}],"nameNarration":"さやか","narration":"なぜか木崎衣美里ちゃんに言われ@次々と試着したあたし","narrationBg":"bg_adv_21041.jpg","narrationEffect":"in","turnChangeIn":"fadeIn","turnChangeOut":"fadeOut"},{"narration":"だけど、やっぱり似合わない…！"},{"chara":[{"id":200401,"motion":300}],"nameLeft":"木崎 衣美里","nameRight":"さやか","narrationEffect":"out","textRight":"[chara:200401:effect_emotion_sad_0][se:7224_fall_into]ごめん、衣美里ちゃん…@あたし、ギブアップ"},{"chara":[{"cheek":0,"face":"mtn_ex_050.exp.json","id":300601,"motion":400}],"textLeft":"[chara:300601:effect_emotion_surprise_0][se:7226_shock]へっ!?@なんでなんで!?"},{"chara":[{"id":300601}],"textLeft":"まだまだ試着する服は@いっぱい残ってるよ？"},{"chara":[{"id":200401,"motion":1}],"textRight":"うーん、なんていうかね@やっぱり、あたしにはさ"},{"chara":[{"id":200401}],"textRight":"カワイイは向いてないって@思っちゃうんだよね…"},{"chara":[{"cheek":0,"face":"mtn_ex_030.exp.json","id":300601,"motion":1}],"textLeft":"そんなことないのにな～"},{"chara":[{"cheek":0,"face":"mtn_ex_010.exp.json","id":200401,"motion":100}],"textRight":"そう言ってもらえるのは…@嬉しいんだけどね！"},{"chara":[{"cheek":0,"face":"mtn_ex_040.exp.json","id":200401}],"textRight":"でも本人が納得できなかったら@デート中そわそわしちゃうし…"},{"chara":[{"eyeClose":1,"id":200401}],"textRight":"それに…"},{"chara":[{"cheek":0,"face":"mtn_ex_050.exp.json","id":300601,"motion":0}],"textLeft":"それに？"},{"chara":[{"cheek":1,"eyeClose":0,"face":"mtn_ex_010.exp.json","id":200401,"motion":300}],"textRight":"あたしの好きな人は…"},{"chara":[{"id":200401}],"textRight":"洋服とか…@外見じゃなくて…"},{"chara":[{"eyeClose":1,"id":200401}],"textRight":"ちゃんと中身で人のことを@判断してくれると思うから…"},{"chara":[{"cheek":0,"face":"mtn_ex_010.exp.json","id":300601,"motion":1}],"textLeft":"…そっか！@いい人だね！"},{"chara":[{"cheek":2,"eyeClose":0,"face":"mtn_ex_011.exp.json","id":200401,"motion":200}],"textRight":"うん、音楽漬けの、音楽バカ！@でも、そこがカッコいいんだ"},{"chara":[{"cheek":1,"face":"mtn_ex_011.exp.json","id":300601,"motion":200}],"textLeft":"[chara:300601:effect_emotion_joy_0][se:7222_happy]キャー！@恋するさやきゃんキャワイイ！"},{"chara":[{"cheek":2,"face":"mtn_ex_050.exp.json","id":200401,"motion":400}],"textRight":"ちょっと@茶化さないでよ…！"},{"chara":[{"cheek":0,"face":"mtn_ex_010.exp.json","id":300601}],"textLeft":"ごめんごめん"},{"chara":[{"cheek":0,"face":"mtn_ex_011.exp.json","id":300601,"motion":100}],"textLeft":"じゃあ最後にね、とっておきの@場所に案内したげる！"},{"chara":[{"cheek":0,"face":"mtn_ex_040.exp.json","id":200401,"motion":0}],"textRight":"とっておき？"},{"chara":[{"cheek":0,"face":"mtn_ex_050.exp.json","id":300601,"motion":1}],"textLeft":"やっぱデートっていうと@ロケーションも大事っしょ？"},{"chara":[{"cheek":0,"face":"mtn_ex_010.exp.json","id":300601}],"textLeft":"だから、乙女の純情爆発で@男子もコロッと一撃の場所にね"},{"chara":[{"id":300601}],"textLeft":"あそこに二人で行けば…@男子の方はメロメロだよ！"},{"chara":[{"cheek":0,"face":"mtn_ex_050.exp.json","id":300601,"motion":400}],"textLeft":"こんな所に連れて来ちゃう君は@ああ！カワイイ！[chara:300601:lipSynch_0][wait:1.0][chara:300601:cheek_0][chara:300601:face_mtn_ex_011.exp.json][chara:300601:lipSynch_1]ってね！"},{"chara":[{"cheek":0,"face":"mtn_ex_050.exp.json","id":200401,"motion":400}],"textRight":"そ、そんな場所が…!?"},{"chara":[{"cheek":0,"face":"mtn_ex_010.exp.json","id":300601,"motion":200}],"textLeft":"そう！スーパーロマンチックな@場所があるんだ！"},{"chara":[{"cheek":0,"face":"mtn_ex_050.exp.json","id":300601}],"textLeft":"知りたい？@ねえ？知りたい？"},{"chara":[{"cheek":0,"face":"mtn_ex_020.exp.json","id":200401,"motion":200}],"textRight":"知りたいです！@是非とも教えてください！"},{"chara":[{"cheek":0,"face":"mtn_ex_011.exp.json","id":300601,"motion":100}],"textLeft":"アイアイサ！"},{"chara":[{"cheek":0,"face":"mtn_ex_010.exp.json","id":300601}],"textLeft":"さやきゃんのために……@秘密の場所を教えちゃうぞ！"},{"chara":[{"cheek":0,"face":"mtn_ex_040.exp.json","id":200401,"motion":0}],"textRight":"秘密の…場所？"},{"autoTurnLast":2.0,"turnChangeIn":"fadeIn"}]},"version":3}