{"story":{"group_1":[{"autoTurnLast":2.0,"chara":[{"cheek":0,"eyeClose":1,"face":"mtn_ex_030.exp.json","id":302601,"motion":0,"pos":0},{"cheek":0,"eyeClose":1,"face":"mtn_ex_030.exp.json","id":302701,"motion":0,"pos":2}],"turnChangeIn":"fadeIn"},{"bg":"bg_adv_21083.jpg","bgm":"bgm03_story02","chara":[{"id":302701,"motion":300}],"nameLeft":"静海 このは","nameRight":"遊佐 葉月","textRight":"うっ…@うーん……","turnChangeOut":"fadeOut"},{"chara":[{"id":302601,"motion":300}],"textLeft":"ま、まさか…@こんなことになるなんて…"},{"chara":[{"id":302601}],"textLeft":"今回は…うまくいくはず…@だったのに…………"},{"chara":[{"cheek":0,"eyeClose":0,"face":"mtn_ex_020.exp.json","id":302601}],"textLeft":"次こそは…必ず…"},{"chara":[{"eyeClose":0,"id":302701,"lipSynch":0}],"textRight":"（料理やめてくれるのが@一番なんだけど…な…）"},{"chara":[{"cheek":0,"face":"mtn_ex_011.exp.json","id":302801,"motion":0,"pos":2}],"nameRight":"三栗 あやめ","textRight":"ただいまー！@…ふたりとも大丈夫？"},{"chara":[{"cheek":0,"face":"mtn_ex_030.exp.json","id":302601,"motion":0}],"textLeft":"お、おかえりなさい@私は、まだ…"},{"chara":[{"cheek":0,"face":"mtn_ex_030.exp.json","id":302701,"motion":0,"pos":0}],"nameLeft":"遊佐 葉月","textLeft":"アタシも…"},{"chara":[{"cheek":0,"face":"mtn_ex_030.exp.json","id":302801}],"textRight":"そっか…"},{"chara":[{"cheek":0,"face":"mtn_ex_010.exp.json","id":302801,"motion":200}],"textRight":"あのね、あちしね！@ふたりに元気になって欲しくて"},{"chara":[{"id":302801}],"textRight":"この絵本に出てくる@“どんな病も治す幻の青い花”を"},{"chara":[{"cheek":0,"face":"mtn_ex_011.exp.json","id":302801,"motion":100}],"textRight":"探しに行ってたんだ"},{"chara":[{"cheek":0,"face":"mtn_ex_050.exp.json","id":302701}],"textLeft":"あっ、それ…@昔よく、読んだよね…"},{"chara":[{"cheek":0,"face":"mtn_ex_010.exp.json","id":302601,"motion":100,"pos":0}],"nameLeft":"静海 このは","textLeft":"あら…@懐かしいわね…"},{"chara":[{"cheek":0,"face":"mtn_ex_030.exp.json","id":302801,"motion":300}],"textRight":"うん@でも…"},{"chara":[{"id":302801}],"textRight":"“どんな病も治す幻の青い花”は@なくて…"},{"chara":[{"cheek":0,"face":"mtn_ex_011.exp.json","id":302801,"motion":200}],"textRight":"その代わり、とってもいいもの@見つけたんだ！"},{"chara":[{"cheek":0,"face":"mtn_ex_050.exp.json","id":302601}],"textLeft":"いいもの…？"},{"chara":[{"cheek":0,"face":"mtn_ex_010.exp.json","id":302801}],"textRight":"うん、これ！"},{"chara":[{"cheek":0,"face":"mtn_ex_011.exp.json","id":302701,"motion":100,"pos":0}],"nameLeft":"遊佐 葉月","textLeft":"青い花！@キレイだね"},{"chara":[{"cheek":0,"face":"mtn_ex_010.exp.json","id":302601,"motion":1,"pos":0}],"nameLeft":"静海 このは","textLeft":"これを私たちのために？@嬉しいわ"},{"chara":[{"cheek":0,"face":"mtn_ex_011.exp.json","id":302801,"motion":100}],"textRight":"[chara:302801:effect_emotion_joy_0][se:7222_happy]ふふーん！@この花はね"},{"chara":[{"id":302801}],"textRight":"元気になってもらいたくて@あちしが作ったの！"},{"chara":[{"cheek":0,"face":"mtn_ex_050.exp.json","id":302601}],"textLeft":"作った？"},{"chara":[{"cheek":0,"face":"mtn_ex_050.exp.json","id":302701,"motion":0,"pos":0}],"nameLeft":"遊佐 葉月","textLeft":"あやめが？"},{"chara":[{"cheek":0,"face":"mtn_ex_010.exp.json","id":302801,"motion":1}],"textRight":"そーだよ！"},{"chara":[{"id":302801}],"textRight":"あちしはね、魔法で@白い花を青く染められるの！"},{"chara":[{"cheek":0,"face":"mtn_ex_011.exp.json","id":302801,"motion":100}],"textRight":"元気になったら@ふたりにもみせてあげる！"},{"chara":[{"cheek":0,"face":"mtn_ex_010.exp.json","id":302701,"motion":1}],"textLeft":"へぇ…@魔法でねぇ"},{"chara":[{"cheek":0,"face":"mtn_ex_010.exp.json","id":302601,"motion":100,"pos":0}],"nameLeft":"静海 このは","textLeft":"ふふっ@それは楽しみだわ"},{"autoTurnLast":2.0,"turnChangeIn":"fadeIn"}]},"version":3}