{"story":{"group_1":[{"bg":"bg_adv_11061.jpg","bgm":"bgm03_story02","chara":[{"cheek":0,"face":"mtn_ex_051.exp.json","id":101700,"motion":200,"pos":0},{"cheek":0,"face":"mtn_ex_000.exp.json","id":302901,"motion":200,"pos":2}],"nameNarration":"みたま","narration":"珍しくひとりで@調整屋に来たまさらちゃんは…","narrationBg":"bg_adv_11061.jpg","narrationEffect":"in","turnChangeIn":"fadeIn","turnChangeOut":"fadeOut","turnEffect":"blackFrame"},{"chara":[{"id":101700}],"nameLeft":"みたま","nameRight":"加賀見 まさら","narrationEffect":"out","textLeft":"熱心に見入っちゃって@[chara:101700:lipSynch_0][wait:1.0][chara:101700:cheek_0][chara:101700:face_mtn_ex_010.exp.json][chara:101700:lipSynch_1]なぁに？それ"},{"chara":[{"cheek":0,"face":"mtn_ex_050.exp.json","id":302901,"motion":0}],"textRight":"え…"},{"chara":[{"cheek":0,"face":"mtn_ex_011.exp.json","id":101700,"motion":100}],"textLeft":"あらっ@ハイキングのチラシじゃない"},{"chara":[{"cheek":0,"face":"mtn_ex_010.exp.json","id":101700}],"textLeft":"そのイベント、興味あるの？"},{"chara":[{"cheek":0,"face":"mtn_ex_000.exp.json","id":302901,"motion":300}],"textRight":"…私は…@別に…"},{"chara":[{"cheek":0,"face":"mtn_ex_051.exp.json","id":101700,"lipSynch":0,"motion":0}],"textLeft":"…？"},{"chara":[{"id":302901,"motion":0}],"textRight":"…あの子が…@話していたから…"},{"chara":[{"effect":"fadeout","id":101700},{"cheek":0,"face":"mtn_ex_000.exp.json","id":302901,"motion":0,"pos":1}],"nameNarration":"みたま","narration":"珍しく思うところがある様子だった","narrationBg":"bg_adv_11061.jpg","narrationEffect":"in"},{"narration":"でも…"},{"chara":[{"id":302901,"motion":300}],"nameCenter":"加賀見 まさら","narrationEffect":"out","textCenter":"…彼女がもう一度…@誰かと山を登るときは…"},{"chara":[{"id":302901}],"textCenter":"それはやっぱり…彼女の家族とで@あるべきだと思うから…"},{"chara":[{"cheek":0,"face":"mtn_ex_000.exp.json","id":302901,"motion":0,"pos":2},{"cheek":0,"face":"mtn_ex_030.exp.json","id":101700,"motion":0,"pos":0}],"nameNarration":"みたま","narration":"どうにも遠慮があるみたいで…","narrationBg":"bg_adv_11061.jpg","narrationEffect":"in"},{"chara":[{"id":101700,"lipSynch":0,"motion":300}],"narrationEffect":"out","textLeft":"（遠慮しないで@誘ってみればいいのに）"},{"chara":[{"id":302901,"motion":100}],"textRight":"じゃあ、私はこれで@ありがとうございました"},{"chara":[{"eyeClose":1,"id":101700,"lipSynch":0}],"textLeft":"（わたしが口を出すことでも@ないけど…う～ん…）"},{"chara":[{"id":101700,"lipSynch":0}],"textLeft":"（なぁ～んか@もやもやするのよねぇ…）"},{"chara":[{"id":302901,"motion":0}],"textRight":"みたまさん…？"},{"chara":[{"cheek":0,"eyeClose":0,"face":"mtn_ex_010.exp.json","id":101700,"motion":1}],"textLeft":"あら、ごめんなさい@ぼんやりしていたみたい"},{"chara":[{"cheek":0,"face":"mtn_ex_011.exp.json","id":101700}],"textLeft":"またいつでも来てねぇ"},{"chara":[{"id":302901}],"textRight":"失礼します…"},{"autoTurnLast":0.2,"chara":[{"effect":"fadeout","id":302901}],"textClear":1},{"chara":[{"cheek":0,"face":"mtn_ex_010.exp.json","id":101700,"lipSynch":0,"motion":0,"pos":1}],"nameCenter":"みたま","textCenter":"（さて、わたしも閉店準備を…）"},{"chara":[{"cheek":0,"face":"mtn_ex_051.exp.json","id":101700}],"textCenter":"…あら？@さっきのチラシ？"},{"chara":[{"cheek":0,"face":"mtn_ex_030.exp.json","id":101700,"lipSynch":0}],"textCenter":"（まさらちゃん、@持っていかなかったのね）"},{"bgm":"stop","chara":[{"cheek":0,"face":"mtn_ex_051.exp.json","id":101700,"lipSynch":0,"motion":400}],"textCenter":"[chara:101700:effect_emotion_surprise_0][se:7226_shock]――っ!?"},{"nameNarration":"","narration":"「１等：超高級ブランド米５kg」","narrationBg":"bg_adv_narration.jpg","narrationEffect":"in"},{"bgm":"bgm03_story16","chara":[{"id":101700}],"narrationEffect":"out","textCenter":"う、うそ…@これって…！"},{"chara":[{"cheek":0,"face":"mtn_ex_011.exp.json","id":101700,"motion":100}],"textCenter":"滅多に手に入らないって有名な@あのブランドのお米じゃない！"},{"chara":[{"cheek":0,"face":"mtn_ex_020.exp.json","id":101700,"lipSynch":0,"motion":0}],"textCenter":"…………"},{"chara":[{"id":101700,"lipSynch":0}],"textCenter":"（登山が趣味のこころちゃん@頭の回転が速いまさらちゃん…）"},{"chara":[{"id":101700,"motion":200}],"textCenter":"いけるわ"},{"chara":[{"cheek":0,"face":"mtn_ex_011.exp.json","id":101700,"lipSynch":0}],"textCenter":"（それにふたりにとっても@きっといい機会だし）"},{"chara":[{"id":101700,"lipSynch":0,"motion":100}],"textCenter":"[chara:101700:effect_emotion_joy_0][se:7222_happy]（たまには、調整屋さん@おせっかいしちゃおうかしらぁ）"},{"chara":[{"cheek":0,"face":"mtn_ex_030.exp.json","id":301601,"motion":0,"pos":1}],"nameNarration":"みたま","narration":"善は急げ！@ということで…","narrationBg":"bg_adv_11061.jpg","narrationEffect":"in"},{"narration":"次の日、調整に来た@まさらちゃんより@説得しやすそうなこころちゃんに@ハイキングのことを話して"},{"chara":[{"id":301601}],"nameCenter":"粟根 こころ","narrationEffect":"out","textCenter":"…じゃぁ～…@[chara:301601:lipSynch_0][wait:1.0][chara:301601:cheek_0][chara:301601:motion_100][chara:301601:face_mtn_ex_011.exp.json][chara:301601:lipSynch_1]ふふっ、参加しよっかな！"},{"nameNarration":"みたま","narration":"参加させることに成功したの","narrationBg":"bg_adv_11061.jpg","narrationEffect":"in"},{"autoTurnLast":0.5,"bgm":"stop","chara":[{"cheek":0,"face":"mtn_ex_010.exp.json","id":101700,"motion":0,"pos":0},{"cheek":0,"face":"mtn_ex_010.exp.json","id":101001,"motion":0,"pos":2}],"narrationEffect":"out","turnChangeIn":"fadeIn","turnEffect":"stop"},{"bgm":"bgm01_anime03","chara":[{"id":101700,"motion":1}],"nameLeft":"みたま","nameRight":"ももこ","textLeft":"はい、調整終わったわよ","turnChangeOut":"fadeOut"},{"chara":[{"cheek":0,"face":"mtn_ex_011.exp.json","id":101001}],"textRight":"どーも@じゃあ、アタシはこれで"},{"chara":[{"id":101700,"motion":0}],"textLeft":"ねぇ、ももこ@やっぱり準備って大切よね？"},{"chara":[{"cheek":0,"face":"mtn_ex_050.exp.json","id":101001,"motion":100}],"textRight":"…準備？なんだよ、突然@今度は何を企んでるんだ？"},{"chara":[{"cheek":0,"face":"mtn_ex_030.exp.json","id":101700,"motion":300}],"textLeft":"企んでるなんて@人聞きの悪いこと言わないで？"},{"chara":[{"cheek":0,"face":"mtn_ex_011.exp.json","id":101700}],"textLeft":"ちょこ～と@おせっかいしようっていうだけよ"},{"chara":[{"cheek":0,"face":"mtn_ex_030.exp.json","id":101001}],"textRight":"…おせっかい、ねぇ…"},{"chara":[{"cheek":0,"face":"mtn_ex_010.exp.json","id":101700,"motion":100}],"textLeft":"ハイキングの差し入れだったら@何がいいかしら？"},{"chara":[{"cheek":0,"face":"mtn_ex_050.exp.json","id":101001,"motion":0}],"textRight":"差し入れ…？@意外とまともに考えているんだな"},{"chara":[{"cheek":0,"face":"mtn_ex_011.exp.json","id":101700}],"textLeft":"そうよぉ@高級なお米がかかってるんだから"},{"chara":[{"cheek":0,"face":"mtn_ex_010.exp.json","id":101001,"motion":200}],"textRight":"…それなら、ドリンクとかは？@ハイキングなら水分は必須だろ？"},{"chara":[{"cheek":0,"face":"mtn_ex_010.exp.json","id":101700,"motion":400}],"textLeft":"あら、いいわねぇ"},{"chara":[{"cheek":0,"face":"mtn_ex_011.exp.json","id":101700,"lipSynch":0}],"textLeft":"（愛情たっぷりの特製ドリンクを@持たせれば優勝間違いなしだわ）","turnEffect":"thinking"},{"chara":[{"cheek":0,"face":"mtn_ex_010.exp.json","id":101700,"lipSynch":0,"motion":0}],"textLeft":"（ふたりにはハイキング用品の@準備もして貰いたいし…）"},{"chara":[{"id":101700,"lipSynch":0}],"textLeft":"（たぶん、明日あたり@調整屋に来るだろうから）"},{"chara":[{"cheek":0,"face":"mtn_ex_011.exp.json","id":101700,"motion":100}],"textLeft":"[chara:101700:effect_emotion_joy_0][se:7222_happy]あれもこれも揃いそうなところへ@レッツゴー、ねっ！","turnEffect":"stop"},{"autoTurnLast":2.0,"turnChangeIn":"fadeIn"}]},"version":3}