{"story":{"group_1":[{"autoTurnLast":0.2,"bg":"bg_adv_21201.jpg","chara":[{"cheek":0,"face":"mtn_ex_030.exp.json","id":100204,"motion":0,"pos":0},{"cheek":0,"face":"mtn_ex_001.exp.json","id":100602,"motion":0,"pos":2}],"turnChangeIn":"fadeIn"},{"bgm":"bgm03_story06","chara":[{"id":100204,"motion":300}],"nameLeft":"やちよ","textLeft":"…そう@都さんがそんなことを…","turnChangeOut":"fadeOut"},{"chara":[{"id":100602,"motion":100}],"nameRight":"みふゆ","textRight":"はい、最早@一刻の猶予もありません"},{"chara":[{"id":100602}],"textRight":"犠牲が出る前に、中央区の@問題だけでも片付けましょう"},{"chara":[{"cheek":0,"face":"mtn_ex_021.exp.json","id":100204,"motion":0}],"textLeft":"と、なると…"},{"chara":[{"id":100602,"motion":200}],"textRight":"はい@十七夜さんとの協力が不可欠です"},{"autoTurnLast":0.01,"chara":[{"effect":"fadeout","id":100602}],"textClear":1},{"chara":[{"cheek":1,"face":"mtn_ex_030.exp.json","id":303701,"motion":0,"pos":2}],"nameRight":"メル","textRight":"七海先輩！みふゆさん！@聞いてください！"},{"chara":[{"cheek":0,"face":"mtn_ex_030.exp.json","id":100204,"motion":200}],"textLeft":"メル！あなたは来て早々…@今、大事な話をしてたのよ"},{"chara":[{"cheek":1,"face":"mtn_ex_020.exp.json","id":303701,"motion":100}],"textRight":"でも！@十七夜さんが酷いんです！"},{"chara":[{"id":303701}],"textRight":"ボクのこと疑っていたですよ！@襲撃犯だって！"},{"chara":[{"cheek":0,"face":"mtn_ex_051.exp.json","id":100204,"motion":400}],"textLeft":"えっ？"},{"chara":[{"cheek":0,"face":"mtn_ex_001.exp.json","id":100602,"motion":1,"pos":0}],"nameLeft":"みふゆ","textLeft":"…その話、初めから@詳しく聞かせてください"},{"autoTurnLast":0.5,"bg":"bg_adv_21021.jpg","bgm":"stop","chara":[{"cheek":0,"face":"mtn_ex_010.exp.json","id":303701,"motion":0,"pos":0},{"cheek":0,"face":"mtn_ex_000.exp.json","id":101601,"motion":1,"pos":2}],"turnChangeIn":"fadeIn","turnEffect":"blackFrame"},{"bgm":"bgm03_story08","chara":[{"id":303701}],"nameRight":"十七夜","textRight":"安名、少しいいか？","turnChangeOut":"fadeOut"},{"chara":[{"cheek":0,"face":"mtn_ex_030.exp.json","id":303701,"motion":200}],"nameLeft":"メル","textLeft":"えー、長いですか？"},{"chara":[{"id":303701}],"textLeft":"今日こそは七海先輩のところに@行きたいです"},{"chara":[{"id":101601,"motion":200}],"textRight":"昨日、中央区に行ったか？"},{"chara":[{"cheek":0,"face":"mtn_ex_050.exp.json","id":303701,"motion":0}],"textLeft":"中央区？@行ってないですよ"},{"chara":[{"id":303701}],"textLeft":"昨日は、補習だったので@大東から出てないです"},{"chara":[{"cheek":0,"face":"mtn_ex_020.exp.json","id":303701,"motion":100}],"textLeft":"っていうか、酷いんですよ！"},{"chara":[{"id":303701}],"textLeft":"ちょっと出席日数が足りないから@って放課後全部補習だったんです"},{"chara":[{"id":101601,"motion":100}],"textRight":"…証明出来る者は？"},{"chara":[{"id":303701,"motion":200}],"textLeft":"先生に聞けばわかりますよ"},{"chara":[{"cheek":1,"id":303701}],"textLeft":"ボクが逃げないようにって@ずぅうううっと見張ってたので"},{"chara":[{"id":101601,"motion":1}],"textRight":"…一緒に来い"},{"chara":[{"cheek":0,"face":"mtn_ex_050.exp.json","id":303701,"motion":400}],"textLeft":"[chara:303701:effect_emotion_surprise_0][se:7226_shock]えっ!?@な、なんなんですか!?"},{"chara":[{"id":101601,"pos":1}],"nameCenter":"十七夜","textCenter":"職員室に行く"},{"bgEffect":"shakeSmall","chara":[{"effect":"slideOutRight","id":303701},{"effect":"slideOutRight","id":101601}],"textBg":"shout","textLeft":"ボクは、七海先輩のところに@行きたいですー！"},{"autoTurnLast":1.0,"chara":[{"cheek":0,"face":"mtn_ex_000.exp.json","id":101601,"motion":0,"pos":2},{"cheek":0,"face":"mtn_ex_020.exp.json","id":303701,"motion":0,"pos":0}],"turnChangeIn":"fadeIn"},{"chara":[{"id":101601,"motion":200}],"textRight":"…本当だったか","turnChangeOut":"fadeOut"},{"chara":[{"id":303701,"motion":100}],"textLeft":"あの、そろそろ説明して@欲しいんですが…"},{"chara":[{"id":101601}],"textRight":"む？@ああ、そうか…そうだった"},{"chara":[{"id":101601,"motion":1}],"textRight":"実は、昨日、中央区で@安名に襲われた魔法少女がいてな"},{"chara":[{"cheek":0,"face":"mtn_ex_050.exp.json","id":303701,"motion":400}],"textLeft":"えぇっ!?@ボ、ボクじゃないです！"},{"chara":[{"id":101601}],"textRight":"それは、わかっている"},{"chara":[{"cheek":0,"face":"mtn_ex_020.exp.json","id":101601,"motion":100}],"textRight":"だが、襲った者は"},{"chara":[{"id":101601}],"textRight":"安名の姿で「あんたの敵」@と、名乗ったらしい"},{"chara":[{"cheek":1,"face":"mtn_ex_020.exp.json","id":303701,"motion":200}],"textLeft":"ボクじゃないです！"},{"chara":[{"cheek":0,"face":"mtn_ex_000.exp.json","id":101601,"motion":200}],"textRight":"わかっている"},{"chara":[{"id":101601}],"textRight":"でなければ、今頃@お仕置きしていたところだ"},{"chara":[{"cheek":0,"face":"mtn_ex_030.exp.json","id":303701,"motion":400}],"textLeft":"ひぇ！だ、誰ですか!?@ボクの名を語る卑怯者は！"},{"chara":[{"cheek":0,"face":"mtn_ex_030.exp.json","id":101601,"motion":1}],"textRight":"それが分かれば苦労はしない"},{"chara":[{"id":101601}],"textRight":"…しかし、事態は思った以上に@複雑なようだな…"},{"autoTurnLast":2.0,"bgm":"stop","turnChangeIn":"fadeIn","turnEffect":"stop"}]},"version":3}