{"story":{"group_1":[{"bg":"bg_adv_46105.jpg","bgm":"bgm01_anime09","chara":[{"cheek":0,"face":"mtn_ex_011.exp.json","id":300600,"motion":100,"pos":0}],"nameLeft":"木崎 衣美里","textLeft":"イエーイ！@魔女倒したしみんな無事だし！","turnChangeIn":"fadeIn","turnChangeOut":"fadeOut"},{"chara":[{"cheek":0,"face":"mtn_ex_010.exp.json","id":300400,"motion":0,"pos":2}],"nameRight":"美凪 ささら","textRight":"やったね！"},{"chara":[{"cheek":0,"face":"mtn_ex_010.exp.json","id":101300,"motion":100,"pos":2}],"nameRight":"竜城 明日香","textRight":"ええ！@任務完了です！"},{"chara":[{"cheek":0,"face":"mtn_ex_010.exp.json","id":300600,"motion":0}],"textLeft":"もうバッチリじゃね？@[chara:300600:cheek_0:face_mtn_ex_011.exp.json:effect_emotion_joy_0][se:7222_happy]野球なら完封勝利っしょ！"},{"chara":[{"cheek":0,"face":"mtn_ex_050.exp.json","id":101300,"motion":0}],"textRight":"かんぷう…@その、野球はあまり詳しく…"},{"chara":[{"cheek":0,"face":"mtn_ex_010.exp.json","id":300600}],"textLeft":"んーまあ@すげーよかったってこと！ね！"},{"chara":[{"cheek":0,"face":"mtn_ex_010.exp.json","id":101300}],"textRight":"そ、そうなんですね！"},{"bg":"bg_adv_11073.jpg","bgChangeEffect":"exitWitchSpace","bgm":"bgm01_anime07","chara":[{"cheek":0,"effect":"emotion_surprise_0","face":"mtn_ex_050.exp.json","id":300600}],"se":"7209_gate_close","textLeft":"おっ！[se:7226_shock]戻ってきた！@[chara:300600:cheek_0:face_mtn_ex_010.exp.json:motion_200]はー、ドキドキしたー！"},{"chara":[{"cheek":0,"effect":"ef_adv_05","face":"mtn_ex_010.exp.json","id":300601,"lipSynch":0,"motion":0,"pos":0}],"se":"7205_magic_girl","textLeft":"[freeze:1]…[chara:300601:lipSynch_1]んじゃー、あーし@家帰るね！"},{"chara":[{"cheek":0,"face":"mtn_ex_001.exp.json","id":300400,"motion":400,"mouthOpen":1,"pos":2}],"nameRight":"美凪 ささら","textRight":"あ、待った！[chara:300400:effect_emotion_surprise_0][se:7226_shock]"},{"chara":[{"cheek":0,"effect":"ef_adv_05","face":"mtn_ex_001.exp.json","id":300401,"lipSynch":0,"motion":0,"pos":2}],"se":"7205_magic_girl","textRight":"[freeze:1]…[chara:300401:lipSynch_1]連絡先、教えてよ！"},{"chara":[{"cheek":1,"face":"mtn_ex_050.exp.json","id":101300,"motion":400,"pos":2}],"nameRight":"竜城 明日香","textRight":"え!?[chara:101300:effect_emotion_surprise_0][se:7226_shock]@…[chara:101300:cheek_1:face_mtn_ex_030.exp.json]では、その、なんというか…"},{"chara":[{"cheek":1,"effect":"ef_adv_05","face":"mtn_ex_030.exp.json","id":101301,"lipSynch":0,"motion":300,"pos":2}],"se":"7205_magic_girl","textRight":"[freeze:1]…[chara:101301:lipSynch_1]わ、私も…"},{"chara":[{"cheek":0,"face":"mtn_ex_010.exp.json","id":300601}],"textLeft":"いーよ！"},{"chara":[{"cheek":0,"face":"mtn_ex_010.exp.json","id":300601,"motion":100,"pos":0}],"nameLeft":"木崎 衣美里","textLeft":"んじゃ、いつでも連絡してよ！@[chara:300601:cheek_0:face_mtn_ex_011.exp.json:effect_emotion_joy_0][se:7222_happy]じゃーねー！","turnChangeIn":"rollIn","turnChangeOut":"rollOut"},{"chara":[{"cheek":0,"face":"mtn_ex_010.exp.json","id":300401,"motion":0,"pos":2}],"nameRight":"美凪 ささら","textRight":"うん、じゃあ！"},{"chara":[{"cheek":0,"face":"mtn_ex_050.exp.json","id":101301,"motion":0,"pos":2},{"effect":"fadeout","id":300601}],"nameRight":"竜城 明日香","textRight":"ま、また！"},{"chara":[{"cheek":0,"face":"mtn_ex_001.exp.json","id":300401,"motion":1,"pos":0}],"nameLeft":"美凪 ささら","textLeft":"…あのさ…"},{"chara":[{"cheek":0,"face":"mtn_ex_050.exp.json","id":101301}],"textRight":"…はい…"},{"chara":[{"cheek":0,"face":"mtn_ex_001.exp.json","id":300401,"motion":300}],"textLeft":"…面白い子、だったよね…"},{"chara":[{"cheek":0,"face":"mtn_ex_050.exp.json","id":101301,"lipSynch":0}],"textRight":"…………"},{"chara":[{"cheek":0,"face":"mtn_ex_050.exp.json","id":101301}],"textRight":"はい…"},{"chara":[{"cheek":0,"face":"mtn_ex_050.exp.json","id":101301,"motion":300}],"textRight":"最初は面食らいましたが@話してみると…"},{"chara":[{"cheek":0,"face":"mtn_ex_041.exp.json","id":300401,"motion":0}],"textLeft":"そうなんだよね…@憎めないっていうか…"},{"chara":[{"cheek":0,"face":"mtn_ex_001.exp.json","id":300401}],"textLeft":"それにさ…@気付いたんだけど…"},{"chara":[{"cheek":0,"face":"mtn_ex_001.exp.json","id":300401}],"textLeft":"あの子、天性の閃きっていうの？@そういうの、持ってない…？"},{"chara":[{"cheek":-1,"face":"mtn_ex_050.exp.json","id":101301,"motion":0}],"textRight":"…実は、今になって@私も思っています…"},{"chara":[{"cheek":-1,"face":"mtn_ex_050.exp.json","id":101301,"motion":100}],"textRight":"使い魔の時、衣美里さんが@即時に動いたから倒せたかも、と"},{"chara":[{"cheek":0,"face":"mtn_ex_001.exp.json","id":300401}],"textLeft":"魔女の時もそうだね…@ハッと気づかせてくれるというか"},{"chara":[{"cheek":0,"face":"mtn_ex_001.exp.json","id":300401,"motion":300}],"textLeft":"…とにかく@何かを持っている気がする…"},{"chara":[{"cheek":-1,"face":"mtn_ex_050.exp.json","id":101301,"motion":0}],"textRight":"ええ…"},{"chara":[{"cheek":0,"face":"mtn_ex_001.exp.json","id":300401,"motion":0}],"textLeft":"もっと話したいね…"},{"chara":[{"cheek":-1,"face":"mtn_ex_050.exp.json","id":101301}],"textRight":"そうですね…@…[chara:101301:cheek_0:motion_100]是非会いましょう！"},{"chara":[{"cheek":0,"face":"mtn_ex_050.exp.json","id":101301,"lipSynch":0}],"textRight":"（木崎衣美里さん…か…）"},{"autoTurnFirst":3.0,"bg":"bg_adv_narration.jpg","bgm":"stop","chara":[{"cheek":0,"face":"mtn_ex_050.exp.json","id":300601,"motion":1,"pos":1,"voice":"vo_char_3006_00_03"}],"nameCenter":"木崎 衣美里","textCenter":"魔法少女も結構大変だね～@ま、でも面白くなりそーじゃん！","turnChangeIn":"fadeIn","turnChangeOut":"fadeOut","turnEffect":"stop"},{"autoTurnFirst":0.7,"chara":[{"cheek":0,"face":"mtn_ex_010.exp.json","id":300601}]},{"autoTurnFirst":3.8,"chara":[{"id":300601,"motion":200}]},{"chara":[{"id":300601}]},{"autoTurnLast":2.0,"turnChangeIn":"fadeIn"}]},"version":3}