{"story":{"group_1":[{"bgm":"bgm03_story06","nameNarration":"いろは","narration":"私がみたまさんと会っている頃@ひなのさんと鶴乃ちゃんは…","narrationBg":"bg_adv_narration.jpg","narrationEffect":"in","turnChangeIn":"fadeIn","turnChangeOut":"fadeOut"},{"bg":"bg_adv_91181.jpg","chara":[{"cheek":0,"face":"mtn_ex_020.exp.json","id":300300,"motion":400,"mouthOpen":1,"pos":2},{"cheek":0,"face":"mtn_ex_001.exp.json","id":100300,"motion":0,"pos":0}],"nameLeft":"鶴乃","nameRight":"都 ひなの","narrationEffect":"out","textBg":"shout","textRight":"おーい！@梨花ー！"},{"chara":[{"id":100300,"motion":101,"mouthOpen":1}],"textBg":"shout","textLeft":"おーい！"},{"chara":[{"id":300300,"motion":200,"mouthOpen":1}],"textBg":"shout","textRight":"おーい！@梨花ー！"},{"chara":[{"cheek":0,"face":"mtn_ex_020.exp.json","id":100300,"motion":201,"mouthOpen":1}],"textBg":"shout","textLeft":"おーい！"},{"chara":[{"cheek":0,"face":"mtn_ex_030.exp.json","id":100300,"motion":0}],"textLeft":"…あの、ちょっと質問"},{"chara":[{"id":300300,"motion":0,"mouthOpen":0}],"textRight":"何だ！"},{"chara":[{"id":100300}],"textLeft":"大声出して呼びかけても@いいのかなーって…"},{"chara":[{"id":300300,"lipSynch":0}],"textRight":"…………"},{"chara":[{"id":100300,"motion":200}],"textLeft":"だってだって！@罠かもしれないんでしょ？"},{"chara":[{"id":100300,"motion":300}],"textLeft":"なのに『ここにいますよ～』@って言ってるような…"},{"chara":[{"cheek":0,"face":"mtn_ex_010.exp.json","id":300300,"motion":100}],"textRight":"それでいいのだ！"},{"chara":[{"cheek":0,"face":"mtn_ex_050.exp.json","id":100300,"motion":100}],"textLeft":"それでいいの…？"},{"chara":[{"cheek":0,"face":"mtn_ex_000.exp.json","id":300300}],"textRight":"呼びかけには@２つの意味がある！"},{"chara":[{"id":300300,"motion":1}],"textRight":"本物の梨花が反応すれば@まずよし！"},{"chara":[{"id":300300}],"textRight":"仮に罠を仕掛けている相手を@呼び出したとしてもよし！"},{"chara":[{"id":300300}],"textRight":"状況に変化が生まれる@ということだからな…"},{"chara":[{"cheek":0,"face":"mtn_ex_030.exp.json","id":300300,"motion":0}],"textRight":"一番避けたいのは@『アクションがないこと』だ"},{"chara":[{"cheek":0,"face":"mtn_ex_030.exp.json","id":100300}],"textLeft":"アクション…@[chara:100300:lipSynch_0][wait:0.8][chara:100300:motion_0][chara:100300:cheek_0][chara:100300:face_mtn_ex_050.exp.json][chara:100300:lipSynch_1]あ、そっか！"},{"chara":[{"cheek":0,"face":"mtn_ex_020.exp.json","id":300300,"motion":200}],"textRight":"何も動きがなければ@事態は進展しない！"},{"chara":[{"cheek":0,"face":"mtn_ex_010.exp.json","id":300300}],"textRight":"藪から何が出てきても@こちらにとっては一歩前進だ"},{"chara":[{"cheek":0,"face":"mtn_ex_010.exp.json","id":100300,"motion":1}],"textLeft":"そうだね！"},{"chara":[{"cheek":0,"face":"mtn_ex_000.exp.json","id":300300,"motion":0}],"textRight":"ただし！どちらに転んでも@対応できる身構えは必要だがな"},{"chara":[{"cheek":0,"face":"mtn_ex_001.exp.json","id":100300,"motion":0}],"textLeft":"そーいうことだったら…！"},{"chara":[{"cheek":0,"face":"mtn_ex_050.exp.json","id":300300}],"textRight":"ん…？@扇を二つ構えてどうした…？"},{"chara":[{"id":100300,"motion":200}],"textLeft":"すぅ～…"},{"chara":[{"id":100300,"motion":201,"mouthOpen":1}],"textBg":"shout","textLeft":"[bgEffect:shakeSmall]うぉぉぉぉぉぉぉぉぉい！"},{"chara":[{"id":300300,"motion":400,"mouthOpen":1}],"textRight":"[chara:300300:effect_emotion_surprise_0][se:7226_shock]うわわわわわ！"},{"chara":[{"id":300300,"mouthOpen":0}],"textRight":"…四方八方にデカい声…！"},{"chara":[{"cheek":0,"face":"mtn_ex_011.exp.json","id":100300,"motion":101}],"textLeft":"これぞ秘技「拡声乱舞」！"},{"chara":[{"cheek":0,"face":"mtn_ex_010.exp.json","id":100300,"motion":0}],"textLeft":"では、説明しよう！"},{"chara":[{"cheek":0,"face":"mtn_ex_030.exp.json","id":300300,"motion":0}],"textRight":"…お、おぉ…"},{"chara":[{"id":100300}],"textLeft":"これはお店の宣伝のために@編み出したのだが…"},{"chara":[{"cheek":0,"face":"mtn_ex_000.exp.json","id":100300,"motion":201}],"textLeft":"近所迷惑になるから封印した@幻の技なのであーる！"},{"chara":[{"id":300300}],"textRight":"…そ、そうか…"},{"chara":[{"cheek":0,"face":"mtn_ex_011.exp.json","id":100300,"motion":100}],"textLeft":"でも、今なら@役に立ちそうだよね！"},{"chara":[{"cheek":0,"face":"mtn_ex_010.exp.json","id":300300}],"textRight":"…確かに！"},{"chara":[{"id":300300,"motion":100}],"textRight":"よし！@もっとカマしてくれ！"},{"chara":[{"cheek":0,"face":"mtn_ex_021.exp.json","id":100300,"motion":200}],"textLeft":"よぉーし！@すぅ～…"},{"bgm":"stop","nameNarration":"？？？","narration":"みゃこ先輩…","narrationBg":"bg_adv_narration.jpg","narrationEffect":"in"},{"chara":[{"cheek":0,"face":"mtn_ex_050.exp.json","id":300300}],"narrationEffect":"out","textRight":"ぬ！@[chara:300300:lipSynch_0][wait:0.8][chara:300300:motion_200][chara:300300:cheek_0][chara:300300:face_mtn_ex_020.exp.json][chara:300300:lipSynch_1]待て！"},{"chara":[{"cheek":0,"face":"mtn_ex_050.exp.json","id":100300,"motion":400}],"textLeft":"うぇ!?@[chara:100300:lipSynch_0][wait:0.8][chara:100300:cheek_0][chara:100300:face_mtn_ex_060.exp.json][chara:100300:lipSynch_1]ゲホゲホッ！"},{"chara":[{"cheek":0,"face":"mtn_ex_030.exp.json","id":100300,"motion":300}],"textLeft":"ちょ、ちょっと！@急に止められると…"},{"chara":[{"cheek":0,"face":"mtn_ex_030.exp.json","id":300300,"motion":0}],"textRight":"…聞こえないか…？"},{"bgm":"bgm03_story13","chara":[{"cheek":0,"face":"mtn_ex_030.exp.json","id":303100,"motion":0,"pos":1}],"nameCenter":"綾野 梨花？","textCenter":"みゃこ先輩…","turnChangeIn":"rollInFast","turnChangeOut":"rollOutFast"},{"chara":[{"cheek":0,"face":"mtn_ex_050.exp.json","id":100300,"motion":400,"pos":0},{"cheek":0,"face":"mtn_ex_030.exp.json","id":300300,"motion":0,"pos":2}],"textLeft":"[chara:100300:effect_emotion_surprise_0][se:7226_shock]あーっ！","turnChangeIn":"fadeIn","turnChangeOut":"fadeOut"},{"chara":[{"cheek":0,"face":"mtn_ex_050.exp.json","id":300300,"motion":400}],"textRight":"梨花…！"},{"bgm":"bgm03_story13","chara":[{"cheek":0,"face":"mtn_ex_030.exp.json","id":303100,"motion":1,"pos":0}],"nameLeft":"綾野 梨花？","textLeft":"あたしを…探しに来たの？"},{"chara":[{"cheek":0,"face":"mtn_ex_020.exp.json","id":300300,"motion":1}],"textRight":"当り前だ！"},{"chara":[{"id":300300}],"textRight":"いきなりさよならと言われて@納得できるか！"},{"chara":[{"id":303100}],"textLeft":"みゃこ先輩…"},{"chara":[{"id":303100}],"textLeft":"放っておいてくれれば@よかったのに…"},{"chara":[{"id":300300,"motion":200}],"textRight":"放っておけるわけないだろ！"},{"chara":[{"cheek":0,"face":"mtn_ex_020.exp.json","id":300300,"motion":0}],"textRight":"…そ、それに…お前は偽者だ！"},{"chara":[{"cheek":0,"face":"mtn_ex_050.exp.json","id":303100,"motion":0}],"textLeft":"…偽者…？@あたしが…？"},{"chara":[{"cheek":0,"face":"mtn_ex_030.exp.json","id":303100}],"textLeft":"そんな…酷い…"},{"chara":[{"id":303100,"motion":400}],"textLeft":"…酷いよ！"},{"chara":[{"cheek":0,"face":"mtn_ex_030.exp.json","id":300300,"motion":300}],"textRight":"くっ…！"},{"chara":[{"cheek":0,"face":"mtn_ex_001.exp.json","id":100300,"motion":0,"pos":0}],"nameLeft":"鶴乃","textLeft":"…どうする？@仕掛ける…？"},{"chara":[{"id":300300,"lipSynch":0}],"textRight":"…………"},{"chara":[{"cheek":0,"face":"mtn_ex_030.exp.json","id":303100,"motion":100,"pos":0}],"nameLeft":"綾野 梨花？","textLeft":"ねぇ…みゃこ先輩！"},{"chara":[{"id":300300,"motion":0}],"textRight":"…か、確証が…"},{"chara":[{"cheek":0,"face":"mtn_ex_040.exp.json","id":100300,"motion":100,"pos":0}],"nameLeft":"鶴乃","textLeft":"確証…？"},{"chara":[{"id":300300}],"textRight":"本物の梨花である可能性も@あるわけだから…"},{"chara":[{"cheek":0,"face":"mtn_ex_050.exp.json","id":100300,"motion":0}],"textLeft":"え～！だってこれがさっき@言ってた『アクション』でしょ？"},{"chara":[{"cheek":0,"face":"mtn_ex_020.exp.json","id":100300,"motion":201}],"textLeft":"だったらこちらも@行動しないと…！"},{"chara":[{"cheek":0,"face":"mtn_ex_020.exp.json","id":300300,"motion":1}],"textRight":"わ、分かってる！"},{"chara":[{"cheek":0,"face":"mtn_ex_030.exp.json","id":300300}],"textRight":"…だが、いざ目の前に@梨花がいると…踏ん切りが…"},{"chara":[{"cheek":0,"face":"mtn_ex_040.exp.json","id":100300,"motion":200}],"textLeft":"そんなぁ！どうするのー！"},{"chara":[{"cheek":0,"face":"mtn_ex_030.exp.json","id":303100,"motion":200,"pos":0}],"nameLeft":"綾野 梨花？","textLeft":"みゃこ先輩…！"},{"chara":[{"id":300300,"motion":0}],"textRight":"り、梨花…！"},{"bgm":"stop","nameNarration":"いろは","narration":"ひなのさん！@鶴乃ちゃん！","narrationBg":"bg_adv_narration.jpg","narrationEffect":"in"},{"chara":[{"cheek":0,"face":"mtn_ex_010.exp.json","id":100300,"motion":101,"pos":0}],"nameLeft":"鶴乃","narrationEffect":"out","textLeft":"おー！@その声は！"},{"chara":[{"cheek":0,"face":"mtn_ex_000.exp.json","id":300300}],"textRight":"…ろっはー！"},{"bgm":"bgm01_battle02","chara":[{"cheek":0,"face":"mtn_ex_041.exp.json","id":100100,"motion":0,"pos":2}],"nameRight":"いろは","textRight":"間に合った…！"},{"chara":[{"cheek":0,"face":"mtn_ex_021.exp.json","id":100100}],"textRight":"みたまさんに聞いてきました！"},{"chara":[{"id":100100,"motion":400}],"textRight":"みたまさんは事情を聞いて@即答で『偽者』だと！"},{"chara":[{"cheek":0,"face":"mtn_ex_020.exp.json","id":100300,"motion":201,"pos":0}],"textLeft":"おお！@だったら…！"},{"chara":[{"cheek":0,"eyeClose":1,"face":"mtn_ex_030.exp.json","id":300300,"motion":0,"pos":2}],"nameRight":"都 ひなの","textRight":"…よし…分かった…"},{"chara":[{"cheek":0,"eyeClose":0,"face":"mtn_ex_020.exp.json","id":300300}],"textRight":"…踏ん切りをつける！"},{"bgm":"stop","chara":[{"cheek":0,"face":"mtn_ex_030.exp.json","id":303100,"lipSynch":0,"motion":0,"pos":0}],"nameLeft":"綾野 梨花？","textLeft":"…[wait:0.8]………"},{"bgm":"bgm01_battle06","chara":[{"cheek":0,"face":"mtn_ex_011.exp.json","id":303190,"motion":0,"pos":2},{"cheek":0,"face":"mtn_ex_011.exp.json","id":303100}],"nameRight":"綾野 梨花？","textRight":"酷いなぁ…みゃこ先輩…"},{"chara":[{"cheek":0,"face":"mtn_ex_050.exp.json","id":100300,"motion":200,"pos":0},{"cheek":0,"face":"mtn_ex_020.exp.json","id":300300,"motion":0,"pos":2}],"nameLeft":"鶴乃","textLeft":"[chara:100300:effect_emotion_surprise_0][se:7226_shock]増えた！"},{"chara":[{"id":300300,"motion":1}],"nameRight":"都 ひなの","textRight":"これで確定だな…！"},{"chara":[{"cheek":0,"face":"mtn_ex_030.exp.json","id":303100,"motion":300,"pos":1},{"cheek":0,"face":"mtn_ex_030.exp.json","id":303190,"motion":0,"pos":0},{"cheek":0,"face":"mtn_ex_030.exp.json","id":303191,"motion":0,"pos":2}],"nameCenter":"綾野 梨花？","textCenter":"みゃこ先輩…@酷いよ…"},{"chara":[{"id":303100,"motion":200},{"id":303190,"motion":400},{"id":303191,"motion":100}],"textCenter":"さよならだよ…@さよならだよ…"},{"autoTurnLast":0.01,"chara":[{"cheek":0,"face":"mtn_ex_050.exp.json","id":100100,"motion":0,"pos":1},{"cheek":0,"face":"mtn_ex_030.exp.json","id":303190,"motion":0,"pos":0},{"cheek":0,"face":"mtn_ex_030.exp.json","id":303191,"motion":0,"pos":2}],"turnChangeIn":"rollInFast"},{"chara":[{"id":100100,"motion":401}],"nameCenter":"いろは","textCenter":"わっ！@囲まれた…！","turnChangeOut":"rollOutFast"},{"autoTurnLast":0.01,"chara":[{"cheek":0,"face":"mtn_ex_050.exp.json","id":100300,"motion":0,"pos":1},{"cheek":0,"face":"mtn_ex_030.exp.json","id":303190,"motion":0,"pos":0},{"cheek":0,"face":"mtn_ex_030.exp.json","id":303191,"motion":0,"pos":2}],"turnChangeIn":"rollInFast"},{"chara":[{"id":100300,"motion":400}],"nameCenter":"鶴乃","textCenter":"なぁ～！@しかも分断された～！","turnChangeOut":"rollOutFast"},{"autoTurnLast":0.01,"chara":[{"cheek":0,"face":"mtn_ex_030.exp.json","id":300300,"motion":0,"pos":1},{"cheek":0,"face":"mtn_ex_030.exp.json","id":303190,"motion":0,"pos":0},{"cheek":0,"face":"mtn_ex_030.exp.json","id":303191,"motion":0,"pos":2}],"turnChangeIn":"rollInFast"},{"chara":[{"id":300300,"motion":400}],"nameCenter":"都 ひなの","textCenter":"しまった…！","turnChangeOut":"rollOutFast"},{"autoTurnLast":0.01,"chara":[{"cheek":0,"face":"mtn_ex_021.exp.json","id":100300,"motion":0,"pos":1},{"cheek":0,"face":"mtn_ex_030.exp.json","id":303190,"motion":0,"pos":0},{"cheek":0,"face":"mtn_ex_030.exp.json","id":303191,"motion":0,"pos":2}],"turnChangeIn":"rollInFast"},{"chara":[{"id":100300,"motion":201}],"nameCenter":"鶴乃","textCenter":"ぬぬぬぬぬ～！@突破だ～！","turnChangeOut":"rollOutFast"},{"autoTurnLast":0.01,"chara":[{"cheek":0,"face":"mtn_ex_030.exp.json","id":303100,"motion":0,"pos":1},{"cheek":0,"face":"mtn_ex_030.exp.json","id":303190,"motion":0,"pos":0},{"cheek":0,"face":"mtn_ex_030.exp.json","id":303191,"motion":0,"pos":2}],"turnChangeIn":"rollInFast"},{"chara":[{"id":303100,"motion":1},{"id":303190,"motion":201},{"id":303191,"motion":300}],"nameCenter":"綾野 梨花？","textCenter":"さよならだよ…@さよならだよ…","turnChangeOut":"rollOutFast"},{"chara":[{"cheek":0,"face":"mtn_ex_050.exp.json","id":100300,"motion":0,"pos":0}],"nameLeft":"鶴乃","nameRight":"いろは","textLeft":"う、うわっ！","turnChangeIn":"rollInFast","turnChangeOut":"rollOutFast"},{"chara":[{"cheek":0,"face":"mtn_ex_050.exp.json","id":100100,"motion":200,"pos":2}],"textRight":"凄い勢いで増殖していく…！"},{"chara":[{"cheek":0,"face":"mtn_ex_020.exp.json","id":300300,"motion":300,"pos":0}],"nameLeft":"都 ひなの","textLeft":"この増殖の勢いは予想外…！"},{"chara":[{"cheek":0,"face":"mtn_ex_030.exp.json","id":300300,"motion":0}],"textLeft":"マズい…！@このままでは…!!"},{"bgm":"stop","nameNarration":"木崎 衣美里","narration":"ちょっと待ったー！","narrationBg":"bg_adv_narration.jpg","narrationEffect":"in"},{"bgm":"bgm01_battle02","chara":[{"cheek":0,"face":"mtn_ex_000.exp.json","id":300300,"motion":400}],"narrationEffect":"out","textLeft":"おお！@来てくれたか！"},{"chara":[{"cheek":0,"face":"mtn_ex_011.exp.json","id":300600,"motion":100,"pos":2}],"nameRight":"木崎 衣美里","textRight":"エミリーの@カムバックだよ！"},{"chara":[{"cheek":0,"face":"mtn_ex_011.exp.json","id":100300,"motion":101,"pos":0}],"nameLeft":"鶴乃","textLeft":"ナイスタイミング！"},{"chara":[{"cheek":0,"face":"mtn_ex_010.exp.json","id":100100,"motion":100,"pos":0}],"nameLeft":"いろは","textLeft":"ということは…！"},{"chara":[{"cheek":0,"face":"mtn_ex_010.exp.json","id":300600,"motion":200}],"textRight":"来てもらったよ！@バッチリな助っ人を！"},{"chara":[{"cheek":0,"face":"mtn_ex_050.exp.json","id":300300,"motion":0,"pos":0}],"nameLeft":"都 ひなの","textLeft":"…む！@お前は…！"},{"autoTurnLast":2.0,"turnChangeIn":"fadeIn"}]},"version":3}